pyside_wrapper_yaboiteedoh/__init__.py
pyside_wrapper_yaboiteedoh/components.py
pyside_wrapper_yaboiteedoh/widgets.py
pyside_wrapper_yaboiteedoh-0.2.11.dist-info/METADATA
pyside_wrapper_yaboiteedoh-0.2.11.dist-info/WHEEL
pyside_wrapper_yaboiteedoh-0.2.11.dist-info/RECORD
