Metadata-Version: 2.3
Name: pyside-wrapper-yaboiteedoh
Version: 0.2.11
Summary: 
Author: yaboiteedoh
Author-email: cook.brandon624@gmail.com
Requires-Python: >=3.12,<3.14
Classifier: Programming Language :: Python :: 3
Classifier: Programming Language :: Python :: 3.12
Classifier: Programming Language :: Python :: 3.13
Requires-Dist: pyside6 (>=6.9.1,<7.0.0)
